preprocess_nlp_jp18/__init__.py
preprocess_nlp_jp18/text_preprocess.py
preprocess_nlp_jp18/__pycache__/__init__.cpython-311.pyc
preprocess_nlp_jp18/__pycache__/text_preprocess.cpython-311.pyc
preprocess_nlp_jp18/data/contractions.json
preprocess_nlp_jp18-0.7.dist-info/LICENSE
preprocess_nlp_jp18-0.7.dist-info/METADATA
preprocess_nlp_jp18-0.7.dist-info/WHEEL
preprocess_nlp_jp18-0.7.dist-info/top_level.txt
preprocess_nlp_jp18-0.7.dist-info/RECORD
