Metadata-Version: 2.1
Name: preprocess_nlp_jp18
Version: 0.7
Summary: This is a text preprocessing package
Author: Jayesh Padiya
License: MIT
Classifier: Programming Language :: Python :: 3
Classifier: License :: OSI Approved :: MIT License
Classifier: Operating System :: OS Independent
Requires-Python: >=3.7
License-File: LICENSE
Requires-Dist: spacy==3.7.6
Requires-Dist: textblob==0.18.0.post0
Requires-Dist: beautifulsoup4
Requires-Dist: nltk==3.9.1
